{
  "annotations": {
    "changelogDate": "20240522234900"
  },
  "applications": "*",
  "enableAudit": true,
  "fields": [
    {
      "fieldName": "uid",
      "fieldType": "String",
      "fieldValidateRules": ["required", "unique", "maxlength"],
      "fieldValidateRulesMaxlength": "11"
    },
    {
      "fieldName": "code",
      "fieldType": "String"
    },
    {
      "fieldName": "name",
      "fieldType": "String"
    },
    {
      "fieldName": "description",
      "fieldType": "String"
    },
    {
      "auditField": true,
      "autoGenerate": true,
      "columnType": "varchar(50)",
      "fieldName": "createdBy",
      "fieldType": "String",
      "nullable": false,
      "readonly": true
    },
    {
      "auditField": true,
      "autoGenerate": true,
      "fieldName": "createdDate",
      "fieldType": "Instant",
      "nullable": false,
      "readonly": true
    },
    {
      "auditField": true,
      "autoGenerate": true,
      "columnType": "varchar(50)",
      "fieldName": "lastModifiedBy",
      "fieldType": "String",
      "nullable": false,
      "readonly": true
    },
    {
      "auditField": true,
      "autoGenerate": true,
      "fieldName": "lastModifiedDate",
      "fieldType": "Instant",
      "nullable": false,
      "readonly": true
    }
  ],
  "incrementalChangelog": false,
  "name": "WarehouseItem",
  "pagination": "pagination",
  "relationships": [],
  "searchEngine": "no",
  "service": "serviceImpl"
}
